async_mvg_api-0.2.8.dist-info/licenses/LICENSE
mvg_api/v1/__init__.py
mvg_api/v1/api.py
mvg_api/v1/mvg.py
mvg_api/v1/schemas/__init__.py
mvg_api/v1/schemas/route.py
mvg_api/v1/schemas/ticker.py
mvg_api/v1/tests/__init__.py
mvg_api/v1/tests/api_tests.py
mvg_api/v2/__init__.py
mvg_api/v2/api.py
mvg_api/v2/mvg.py
mvg_api/v2/schemas/__init__.py
mvg_api/v2/schemas/aushang.py
mvg_api/v2/schemas/ems.py
mvg_api/v2/schemas/location.py
mvg_api/v2/schemas/station.py
mvg_api/v2/schemas/transportdevice.py
mvg_api/v2/tests/api_tests.py
async_mvg_api-0.2.8.dist-info/METADATA
async_mvg_api-0.2.8.dist-info/WHEEL
async_mvg_api-0.2.8.dist-info/top_level.txt
async_mvg_api-0.2.8.dist-info/RECORD
