Metadata-Version: 2.4
Name: async_mvg_api
Version: 0.2.8
Author-email: Lukas Mahr <lukas@yousuckatprogramming.de>
Project-URL: Homepage, https://github.com/Plutokekz/MVG-Api
Project-URL: Source, https://github.com/Plutokekz/MVG-Api
Requires-Python: >=3.13
License-File: LICENSE
Requires-Dist: dill>=0.4.0
Requires-Dist: httpx>=0.28.1
Requires-Dist: levenshtein>=0.27.1
Requires-Dist: pydantic>=2.11.4
Requires-Dist: setuptools>=78.1.0
Requires-Dist: wheel>=0.45.1
Dynamic: license-file
